dnasecure/__init__.py
dnasecure/__main__.py
dnasecure/cli.py
dnasecure/core.py
dnasecure-0.0.4.dist-info/LICENSE
dnasecure-0.0.4.dist-info/METADATA
dnasecure-0.0.4.dist-info/WHEEL
dnasecure-0.0.4.dist-info/entry_points.txt
dnasecure-0.0.4.dist-info/top_level.txt
dnasecure-0.0.4.dist-info/RECORD
