Metadata-Version: 2.2
Name: dnasecure
Version: 0.0.4
Summary: DNA sequence encryption and security using self-power decomposition
Author-email: Richard Daodu <lordrichado@gmail.com>
License: MIT
Project-URL: Homepage, https://github.com/joirichi/dnasecure
Project-URL: Bug Tracker, https://github.com/joirichi/dnasecure/issues
Classifier: Programming Language :: Python :: 3
Classifier: License :: OSI Approved :: MIT License
Classifier: Operating System :: OS Independent
Classifier: Topic :: Scientific/Engineering :: Bio-Informatics
Classifier: Topic :: Security :: Cryptography
Requires-Python: >=3.6
License-File: LICENSE
Requires-Dist: selfpowerdecomposer>=0.1.1
Requires-Dist: numpy>=1.19.0
Requires-Dist: biopython>=1.79
Provides-Extra: dev
Requires-Dist: pytest>=7.0.0; extra == "dev"
Requires-Dist: pytest-cov>=4.0.0; extra == "dev"
Requires-Dist: black>=23.0.0; extra == "dev"
Requires-Dist: isort>=5.12.0; extra == "dev"
Requires-Dist: flake8>=6.0.0; extra == "dev"
Requires-Dist: mypy>=1.0.0; extra == "dev"
Requires-Dist: build>=1.0.0; extra == "dev"
Requires-Dist: twine>=4.0.0; extra == "dev"
